check_pack/check_pack.py
funproject_SV-0.0.1.dist-info/METADATA
funproject_SV-0.0.1.dist-info/WHEEL
funproject_SV-0.0.1.dist-info/top_level.txt
funproject_SV-0.0.1.dist-info/RECORD
