Metadata-Version: 2.1
Name: funproject-SV
Version: 0.0.1
Summary: funproject_by_sv
Home-page: https://sv.com
Author: SV
Author-email: sv@ap.com
License: UNKNOWN
Platform: UNKNOWN
